{
"meta":{"test_sets":[],"test_metrics":[],"learn_metrics":[{"best_value":"Min","name":"RMSE"}],"launch_mode":"Train","parameters":"","iteration_count":600,"learn_sets":["learn"],"name":"experiment"},
"iterations":[
{"learn":[12450.69072],"iteration":0,"passed_time":0.004380275305,"remaining_time":2.623784908},
{"learn":[12163.31033],"iteration":1,"passed_time":0.008175013356,"remaining_time":2.444328994},
{"learn":[11901.1802],"iteration":2,"passed_time":0.01394430277,"remaining_time":2.774916251},
{"learn":[11658.28608],"iteration":3,"passed_time":0.01960305901,"remaining_time":2.920855793},
{"learn":[11438.28029],"iteration":4,"passed_time":0.02388742597,"remaining_time":2.842603691},
{"learn":[11194.39754],"iteration":5,"passed_time":0.02848130922,"remaining_time":2.819649613},
{"learn":[10958.29747],"iteration":6,"passed_time":0.03320918178,"remaining_time":2.813292114},
{"learn":[10747.42361],"iteration":7,"passed_time":0.03542825462,"remaining_time":2.621690842},
{"learn":[10594.52137],"iteration":8,"passed_time":0.03702233536,"remaining_time":2.431133355},
{"learn":[10422.40567],"iteration":9,"passed_time":0.03885835578,"remaining_time":2.292642991},
{"learn":[10253.86021],"iteration":10,"passed_time":0.04183174341,"remaining_time":2.239899715},
{"learn":[10102.02437],"iteration":11,"passed_time":0.04437866508,"remaining_time":2.174554589},
{"learn":[9935.902207],"iteration":12,"passed_time":0.0462773055,"remaining_time":2.089598333},
{"learn":[9774.204125],"iteration":13,"passed_time":0.04782155722,"remaining_time":2.001673752},
{"learn":[9629.423431],"iteration":14,"passed_time":0.04966361916,"remaining_time":1.936881147},
{"learn":[9487.18434],"iteration":15,"passed_time":0.0519014405,"remaining_time":1.894402578},
{"learn":[9358.581603],"iteration":16,"passed_time":0.05359955494,"remaining_time":1.838149443},
{"learn":[9245.960103],"iteration":17,"passed_time":0.05504835527,"remaining_time":1.77989682},
{"learn":[9129.335291],"iteration":18,"passed_time":0.05685871074,"remaining_time":1.738679523},
{"learn":[9032.503935],"iteration":19,"passed_time":0.05874364426,"remaining_time":1.703565684},
{"learn":[8913.040282],"iteration":20,"passed_time":0.0614413039,"remaining_time":1.694024522},
{"learn":[8792.296356],"iteration":21,"passed_time":0.06336381742,"remaining_time":1.664740294},
{"learn":[8699.433985],"iteration":22,"passed_time":0.06491031895,"remaining_time":1.628402349},
{"learn":[8621.129652],"iteration":23,"passed_time":0.06676825363,"remaining_time":1.602438087},
{"learn":[8542.164821],"iteration":24,"passed_time":0.06869080914,"remaining_time":1.57988861},
{"learn":[8456.872765],"iteration":25,"passed_time":0.07030509727,"remaining_time":1.552120224},
{"learn":[8385.765299],"iteration":26,"passed_time":0.07261678772,"remaining_time":1.541089606},
{"learn":[8320.3688],"iteration":27,"passed_time":0.07457946503,"remaining_time":1.523551928},
{"learn":[8242.599597],"iteration":28,"passed_time":0.07673600086,"remaining_time":1.510905396},
{"learn":[8175.701035],"iteration":29,"passed_time":0.07840411769,"remaining_time":1.489678236},
{"learn":[8102.793839],"iteration":30,"passed_time":0.08024451176,"remaining_time":1.472875071},
{"learn":[8027.323223],"iteration":31,"passed_time":0.08205753302,"remaining_time":1.456521211},
{"learn":[7958.779138],"iteration":32,"passed_time":0.08375806426,"remaining_time":1.439115831},
{"learn":[7899.46892],"iteration":33,"passed_time":0.08588385255,"remaining_time":1.429713545},
{"learn":[7841.851372],"iteration":34,"passed_time":0.08779199222,"remaining_time":1.417213589},
{"learn":[7801.911284],"iteration":35,"passed_time":0.08949231448,"remaining_time":1.40204626},
{"learn":[7736.410373],"iteration":36,"passed_time":0.09162189446,"remaining_time":1.394138556},
{"learn":[7680.368278],"iteration":37,"passed_time":0.09366235656,"remaining_time":1.385216958},
{"learn":[7626.963225],"iteration":38,"passed_time":0.09551379176,"remaining_time":1.373929158},
{"learn":[7572.993507],"iteration":39,"passed_time":0.09717145142,"remaining_time":1.36040032},
{"learn":[7526.270579],"iteration":40,"passed_time":0.09882102873,"remaining_time":1.347340367},
{"learn":[7481.119384],"iteration":41,"passed_time":0.1004398585,"remaining_time":1.334415263},
{"learn":[7433.75091],"iteration":42,"passed_time":0.1020526887,"remaining_time":1.321938317},
{"learn":[7388.318157],"iteration":43,"passed_time":0.1039572457,"remaining_time":1.313641559},
{"learn":[7351.776905],"iteration":44,"passed_time":0.1062509796,"remaining_time":1.310428748},
{"learn":[7318.578802],"iteration":45,"passed_time":0.1081713683,"remaining_time":1.302759522},
{"learn":[7292.27856],"iteration":46,"passed_time":0.1098627742,"remaining_time":1.292640726},
{"learn":[7255.188412],"iteration":47,"passed_time":0.11175754,"remaining_time":1.285211709},
{"learn":[7218.082532],"iteration":48,"passed_time":0.1137316324,"remaining_time":1.278900601},
{"learn":[7181.836229],"iteration":49,"passed_time":0.1155561947,"remaining_time":1.271118142},
{"learn":[7149.965791],"iteration":50,"passed_time":0.117430795,"remaining_time":1.26410797},
{"learn":[7123.671371],"iteration":51,"passed_time":0.1207931516,"remaining_time":1.272973982},
{"learn":[7092.18439],"iteration":52,"passed_time":0.1255318983,"remaining_time":1.295583931},
{"learn":[7059.287058],"iteration":53,"passed_time":0.1289568749,"remaining_time":1.30389729},
{"learn":[7027.05358],"iteration":54,"passed_time":0.131159657,"remaining_time":1.299672965},
{"learn":[7004.451855],"iteration":55,"passed_time":0.1329370151,"remaining_time":1.291388147},
{"learn":[6978.944597],"iteration":56,"passed_time":0.1345716346,"remaining_time":1.281971888},
{"learn":[6951.012606],"iteration":57,"passed_time":0.1364668993,"remaining_time":1.275259645},
{"learn":[6929.794729],"iteration":58,"passed_time":0.1388094623,"remaining_time":1.272812188},
{"learn":[6906.856243],"iteration":59,"passed_time":0.1407371004,"remaining_time":1.266633904},
{"learn":[6882.112883],"iteration":60,"passed_time":0.142621283,"remaining_time":1.260211009},
{"learn":[6860.584896],"iteration":61,"passed_time":0.14437506,"remaining_time":1.25280294},
{"learn":[6838.633283],"iteration":62,"passed_time":0.1459802648,"remaining_time":1.244307972},
{"learn":[6821.486002],"iteration":63,"passed_time":0.1476173011,"remaining_time":1.236294897},
{"learn":[6808.351732],"iteration":64,"passed_time":0.1494574872,"remaining_time":1.230150087},
{"learn":[6785.091608],"iteration":65,"passed_time":0.1513962904,"remaining_time":1.224933623},
{"learn":[6772.014306],"iteration":66,"passed_time":0.1532603076,"remaining_time":1.219220059},
{"learn":[6758.15471],"iteration":67,"passed_time":0.1551693632,"remaining_time":1.213972077},
{"learn":[6739.359437],"iteration":68,"passed_time":0.1569438046,"remaining_time":1.207784931},
{"learn":[6722.414328],"iteration":69,"passed_time":0.1588282791,"remaining_time":1.20255697},
{"learn":[6706.757498],"iteration":70,"passed_time":0.1608305363,"remaining_time":1.198300756},
{"learn":[6695.697929],"iteration":71,"passed_time":0.1624205753,"remaining_time":1.191084219},
{"learn":[6682.172937],"iteration":72,"passed_time":0.1642811348,"remaining_time":1.185974768},
{"learn":[6668.255567],"iteration":73,"passed_time":0.1659338778,"remaining_time":1.179475943},
{"learn":[6657.534625],"iteration":74,"passed_time":0.1679211772,"remaining_time":1.17544824},
{"learn":[6640.602196],"iteration":75,"passed_time":0.1697438647,"remaining_time":1.170339278},
{"learn":[6627.48897],"iteration":76,"passed_time":0.1719349818,"remaining_time":1.167818123},
{"learn":[6616.848531],"iteration":77,"passed_time":0.1737830002,"remaining_time":1.163009309},
{"learn":[6602.918951],"iteration":78,"passed_time":0.1757132211,"remaining_time":1.158817572},
{"learn":[6589.059027],"iteration":79,"passed_time":0.1773424661,"remaining_time":1.152726029},
{"learn":[6578.811832],"iteration":80,"passed_time":0.1789424633,"remaining_time":1.146557265},
{"learn":[6567.472447],"iteration":81,"passed_time":0.1805932065,"remaining_time":1.1408205},
{"learn":[6554.008772],"iteration":82,"passed_time":0.1822022861,"remaining_time":1.134922673},
{"learn":[6544.105814],"iteration":83,"passed_time":0.1841160083,"remaining_time":1.130998337},
{"learn":[6530.338911],"iteration":84,"passed_time":0.1860475211,"remaining_time":1.127229098},
{"learn":[6517.604398],"iteration":85,"passed_time":0.1882009742,"remaining_time":1.124829078},
{"learn":[6507.215414],"iteration":86,"passed_time":0.1905719099,"remaining_time":1.123717124},
{"learn":[6499.722983],"iteration":87,"passed_time":0.192160991,"remaining_time":1.118027584},
{"learn":[6488.154949],"iteration":88,"passed_time":0.1940221754,"remaining_time":1.11399249},
{"learn":[6476.150972],"iteration":89,"passed_time":0.1958998165,"remaining_time":1.11009896},
{"learn":[6464.195269],"iteration":90,"passed_time":0.197847703,"remaining_time":1.106642647},
{"learn":[6451.758754],"iteration":91,"passed_time":0.2008143412,"remaining_time":1.108844406},
{"learn":[6446.261154],"iteration":92,"passed_time":0.202520705,"remaining_time":1.104064488},
{"learn":[6439.014648],"iteration":93,"passed_time":0.2046982401,"remaining_time":1.101886271},
{"learn":[6427.039837],"iteration":94,"passed_time":0.2065882562,"remaining_time":1.098179678},
{"learn":[6413.564465],"iteration":95,"passed_time":0.2085743057,"remaining_time":1.095015105},
{"learn":[6403.560454],"iteration":96,"passed_time":0.2104694874,"remaining_time":1.09140363},
{"learn":[6394.848745],"iteration":97,"passed_time":0.2123116323,"remaining_time":1.087555504},
{"learn":[6385.085083],"iteration":98,"passed_time":0.2140919902,"remaining_time":1.083435223},
{"learn":[6376.060143],"iteration":99,"passed_time":0.2158180194,"remaining_time":1.079090097},
{"learn":[6367.123486],"iteration":100,"passed_time":0.2174300157,"remaining_time":1.074233444},
{"learn":[6357.73236],"iteration":101,"passed_time":0.2195953428,"remaining_time":1.072141968},
{"learn":[6350.865901],"iteration":102,"passed_time":0.2214996908,"remaining_time":1.06878977},
{"learn":[6340.012288],"iteration":103,"passed_time":0.2231294777,"remaining_time":1.064155971},
{"learn":[6333.144199],"iteration":104,"passed_time":0.2246750623,"remaining_time":1.059182437},
{"learn":[6327.07316],"iteration":105,"passed_time":0.2265309141,"remaining_time":1.055719543},
{"learn":[6321.12554],"iteration":106,"passed_time":0.2282049055,"remaining_time":1.05144877},
{"learn":[6313.050036],"iteration":107,"passed_time":0.2300959215,"remaining_time":1.048214754},
{"learn":[6307.412413],"iteration":108,"passed_time":0.2319911042,"remaining_time":1.045024148},
{"learn":[6297.352821],"iteration":109,"passed_time":0.2339149506,"remaining_time":1.04198478},
{"learn":[6291.941272],"iteration":110,"passed_time":0.2357506371,"remaining_time":1.038577131},
{"learn":[6285.240162],"iteration":111,"passed_time":0.2375599926,"remaining_time":1.035082825},
{"learn":[6274.311197],"iteration":112,"passed_time":0.2393983039,"remaining_time":1.031743133},
{"learn":[6267.253465],"iteration":113,"passed_time":0.24120116,"remaining_time":1.028278629},
{"learn":[6260.391626],"iteration":114,"passed_time":0.2427705767,"remaining_time":1.023858519},
{"learn":[6255.390169],"iteration":115,"passed_time":0.244582974,"remaining_time":1.020501374},
{"learn":[6247.335727],"iteration":116,"passed_time":0.2464145778,"remaining_time":1.017249924},
{"learn":[6241.532117],"iteration":117,"passed_time":0.2479947436,"remaining_time":1.012995478},
{"learn":[6234.237648],"iteration":118,"passed_time":0.2500197479,"remaining_time":1.010584023},
{"learn":[6228.504538],"iteration":119,"passed_time":0.2517995638,"remaining_time":1.007198255},
{"learn":[6221.494573],"iteration":120,"passed_time":0.2536834964,"remaining_time":1.004251197},
{"learn":[6216.776544],"iteration":121,"passed_time":0.2557869945,"remaining_time":1.002181831},
{"learn":[6212.437355],"iteration":122,"passed_time":0.2576777186,"remaining_time":0.9992867623},
{"learn":[6202.900153],"iteration":123,"passed_time":0.2593905398,"remaining_time":0.9957249755},
{"learn":[6195.65405],"iteration":124,"passed_time":0.2613620914,"remaining_time":0.9931759474},
{"learn":[6188.067679],"iteration":125,"passed_time":0.2631864038,"remaining_time":0.9900821857},
{"learn":[6179.719404],"iteration":126,"passed_time":0.2648291886,"remaining_time":0.9863323325},
{"learn":[6173.809939],"iteration":127,"passed_time":0.2665105544,"remaining_time":0.9827576694},
{"learn":[6164.042704],"iteration":128,"passed_time":0.2690313122,"remaining_time":0.9822771165},
{"learn":[6155.345044],"iteration":129,"passed_time":0.2710956054,"remaining_time":0.9801148809},
{"learn":[6152.436951],"iteration":130,"passed_time":0.2730833217,"remaining_time":0.9776799837},
{"learn":[6147.777039],"iteration":131,"passed_time":0.2749895865,"remaining_time":0.9749630794},
{"learn":[6141.877434],"iteration":132,"passed_time":0.2768651038,"remaining_time":0.9721504019},
{"learn":[6134.822842],"iteration":133,"passed_time":0.2787686608,"remaining_time":0.9694492234},
{"learn":[6130.024368],"iteration":134,"passed_time":0.2803878235,"remaining_time":0.9657802811},
{"learn":[6124.633957],"iteration":135,"passed_time":0.2822745889,"remaining_time":0.9630544798},
{"learn":[6120.993023],"iteration":136,"passed_time":0.2841255241,"remaining_time":0.9602198371},
{"learn":[6116.587905],"iteration":137,"passed_time":0.2858753014,"remaining_time":0.9570607918},
{"learn":[6111.86188],"iteration":138,"passed_time":0.2877427364,"remaining_time":0.9543122407},
{"learn":[6106.165294],"iteration":139,"passed_time":0.2895711314,"remaining_time":0.9514480032},
{"learn":[6100.151384],"iteration":140,"passed_time":0.2911015512,"remaining_time":0.947628454},
{"learn":[6096.618372],"iteration":141,"passed_time":0.2930698941,"remaining_time":0.945253602},
{"learn":[6090.16959],"iteration":142,"passed_time":0.2947226371,"remaining_time":0.9418758403},
{"learn":[6085.220215],"iteration":143,"passed_time":0.2965724894,"remaining_time":0.9391462166},
{"learn":[6079.386925],"iteration":144,"passed_time":0.2984783373,"remaining_time":0.9366044377},
{"learn":[6076.99806],"iteration":145,"passed_time":0.3014137699,"remaining_time":0.9372729559},
{"learn":[6070.435999],"iteration":146,"passed_time":0.3031854615,"remaining_time":0.9343062181},
{"learn":[6064.471961],"iteration":147,"passed_time":0.3047193391,"remaining_time":0.9306293328},
{"learn":[6061.228062],"iteration":148,"passed_time":0.3063709992,"remaining_time":0.9273377224},
{"learn":[6053.992523],"iteration":149,"passed_time":0.3081634391,"remaining_time":0.9244903173},
{"learn":[6047.855387],"iteration":150,"passed_time":0.3097753934,"remaining_time":0.9211202095},
{"learn":[6044.180246],"iteration":151,"passed_time":0.3116031225,"remaining_time":0.9184092031},
{"learn":[6035.576695],"iteration":152,"passed_time":0.3138479013,"remaining_time":0.9169281822},
{"learn":[6031.733476],"iteration":153,"passed_time":0.315455106,"remaining_time":0.9135907615},
{"learn":[6028.061192],"iteration":154,"passed_time":0.3172904595,"remaining_time":0.9109306739},
{"learn":[6019.765705],"iteration":155,"passed_time":0.3191684345,"remaining_time":0.9084024675},
{"learn":[6017.388125],"iteration":156,"passed_time":0.3208145531,"remaining_time":0.905228325},
{"learn":[6014.501622],"iteration":157,"passed_time":0.3225792462,"remaining_time":0.9024052331},
{"learn":[6009.275865],"iteration":158,"passed_time":0.3246558304,"remaining_time":0.9004605109},
{"learn":[6005.238885],"iteration":159,"passed_time":0.326440605,"remaining_time":0.8977116636},
{"learn":[6000.960514],"iteration":160,"passed_time":0.3282826239,"remaining_time":0.8951308813},
{"learn":[5995.993562],"iteration":161,"passed_time":0.3303393347,"remaining_time":0.8931396827},
{"learn":[5991.307997],"iteration":162,"passed_time":0.335684241,"remaining_time":0.8999632719},
{"learn":[5986.618225],"iteration":163,"passed_time":0.3411630536,"remaining_time":0.9069944596},
{"learn":[5982.206655],"iteration":164,"passed_time":0.3459144243,"remaining_time":0.9119562095},
{"learn":[5976.306708],"iteration":165,"passed_time":0.3498804827,"remaining_time":0.9147477679},
{"learn":[5972.026699],"iteration":166,"passed_time":0.3537260097,"remaining_time":0.9171458813},
{"learn":[5969.029343],"iteration":167,"passed_time":0.3557291827,"remaining_time":0.9147321842},
{"learn":[5963.567149],"iteration":168,"passed_time":0.3575144982,"remaining_time":0.9117677439},
{"learn":[5961.106517],"iteration":169,"passed_time":0.3593287284,"remaining_time":0.9088903129},
{"learn":[5958.557246],"iteration":170,"passed_time":0.361037342,"remaining_time":0.9057603491},
{"learn":[5955.366045],"iteration":171,"passed_time":0.3626993753,"remaining_time":0.9025310036},
{"learn":[5950.287336],"iteration":172,"passed_time":0.3648489117,"remaining_time":0.9005230363},
{"learn":[5947.082714],"iteration":173,"passed_time":0.3667685084,"remaining_time":0.8979504861},
{"learn":[5942.835216],"iteration":174,"passed_time":0.3687730984,"remaining_time":0.8955918104},
{"learn":[5936.905561],"iteration":175,"passed_time":0.3706478657,"remaining_time":0.8929244038},
{"learn":[5931.805161],"iteration":176,"passed_time":0.3725934604,"remaining_time":0.8904352189},
{"learn":[5928.80351],"iteration":177,"passed_time":0.374314656,"remaining_time":0.8874201395},
{"learn":[5924.728907],"iteration":178,"passed_time":0.3762345027,"remaining_time":0.8848867354},
{"learn":[5921.211666],"iteration":179,"passed_time":0.3782501748,"remaining_time":0.8825837412},
{"learn":[5915.564457],"iteration":180,"passed_time":0.3805062867,"remaining_time":0.88084052},
{"learn":[5912.184541],"iteration":181,"passed_time":0.3861130471,"remaining_time":0.8867871081},
{"learn":[5908.31071],"iteration":182,"passed_time":0.3913525038,"remaining_time":0.8917704594},
{"learn":[5904.879737],"iteration":183,"passed_time":0.3932473525,"remaining_time":0.8890809709},
{"learn":[5901.740157],"iteration":184,"passed_time":0.3949056371,"remaining_time":0.8858694022},
{"learn":[5896.036688],"iteration":185,"passed_time":0.3966626219,"remaining_time":0.8828942228},
{"learn":[5890.229317],"iteration":186,"passed_time":0.3982249551,"remaining_time":0.8795021736},
{"learn":[5887.536786],"iteration":187,"passed_time":0.3997205857,"remaining_time":0.8759834113},
{"learn":[5883.097569],"iteration":188,"passed_time":0.4015819791,"remaining_time":0.8732814467},
{"learn":[5875.554671],"iteration":189,"passed_time":0.4031027327,"remaining_time":0.8698532653},
{"learn":[5871.416815],"iteration":190,"passed_time":0.4047509761,"remaining_time":0.8667180588},
{"learn":[5869.747115],"iteration":191,"passed_time":0.4065961628,"remaining_time":0.864016846},
{"learn":[5863.116888],"iteration":192,"passed_time":0.4086961622,"remaining_time":0.8618618549},
{"learn":[5857.368279],"iteration":193,"passed_time":0.4103361982,"remaining_time":0.8587448272},
{"learn":[5854.54102],"iteration":194,"passed_time":0.4121405132,"remaining_time":0.8559841428},
{"learn":[5849.253815],"iteration":195,"passed_time":0.4141161895,"remaining_time":0.8535864314},
{"learn":[5843.601274],"iteration":196,"passed_time":0.4160941566,"remaining_time":0.8511976908},
{"learn":[5839.332324],"iteration":197,"passed_time":0.4177464417,"remaining_time":0.8481518664},
{"learn":[5835.350435],"iteration":198,"passed_time":0.4196487068,"remaining_time":0.845623776},
{"learn":[5830.584284],"iteration":199,"passed_time":0.4214083163,"remaining_time":0.8428166326},
{"learn":[5827.953682],"iteration":200,"passed_time":0.4231508442,"remaining_time":0.8399860042},
{"learn":[5824.539665],"iteration":201,"passed_time":0.4248345428,"remaining_time":0.8370502378},
{"learn":[5820.943919],"iteration":202,"passed_time":0.4266791865,"remaining_time":0.8344415618},
{"learn":[5818.307296],"iteration":203,"passed_time":0.4290732034,"remaining_time":0.8329068066},
{"learn":[5812.967136],"iteration":204,"passed_time":0.4307595688,"remaining_time":0.8300001447},
{"learn":[5810.530441],"iteration":205,"passed_time":0.432585881,"remaining_time":0.8273729956},
{"learn":[5808.736017],"iteration":206,"passed_time":0.4341237162,"remaining_time":0.824205896},
{"learn":[5802.315316],"iteration":207,"passed_time":0.4360694779,"remaining_time":0.8218232467},
{"learn":[5799.358214],"iteration":208,"passed_time":0.4377726749,"remaining_time":0.8189909851},
{"learn":[5794.76264],"iteration":209,"passed_time":0.4396991041,"remaining_time":0.8165840504},
{"learn":[5791.347952],"iteration":210,"passed_time":0.441541665,"remaining_time":0.8140270506},
{"learn":[5789.529763],"iteration":211,"passed_time":0.4438537304,"remaining_time":0.8123360726},
{"learn":[5783.77799],"iteration":212,"passed_time":0.4454933075,"remaining_time":0.8094174179},
{"learn":[5777.945981],"iteration":213,"passed_time":0.447366325,"remaining_time":0.8069317824},
{"learn":[5773.688262],"iteration":214,"passed_time":0.4493937051,"remaining_time":0.8047282627},
{"learn":[5771.773923],"iteration":215,"passed_time":0.4510518228,"remaining_time":0.8018699071},
{"learn":[5768.948173],"iteration":216,"passed_time":0.4529607954,"remaining_time":0.7994653669},
{"learn":[5766.107442],"iteration":217,"passed_time":0.454593331,"remaining_time":0.7965809745},
{"learn":[5764.184042],"iteration":218,"passed_time":0.4563442742,"remaining_time":0.7939140113},
{"learn":[5762.801794],"iteration":219,"passed_time":0.4582585384,"remaining_time":0.7915374754},
{"learn":[5760.273878],"iteration":220,"passed_time":0.4599624854,"remaining_time":0.7888044433},
{"learn":[5756.922499],"iteration":221,"passed_time":0.4623320882,"remaining_time":0.7872140961},
{"learn":[5752.809817],"iteration":222,"passed_time":0.4643500101,"remaining_time":0.7850222144},
{"learn":[5749.766055],"iteration":223,"passed_time":0.4672654434,"remaining_time":0.7843384228},
{"learn":[5746.6636],"iteration":224,"passed_time":0.4688289025,"remaining_time":0.7813815042},
{"learn":[5743.006358],"iteration":225,"passed_time":0.4704061516,"remaining_time":0.7784597376},
{"learn":[5739.5969],"iteration":226,"passed_time":0.4722532542,"remaining_time":0.7759932326},
{"learn":[5733.714442],"iteration":227,"passed_time":0.4741329791,"remaining_time":0.7735853869},
{"learn":[5729.07934],"iteration":228,"passed_time":0.4760768649,"remaining_time":0.7712860999},
{"learn":[5727.17024],"iteration":229,"passed_time":0.4778783461,"remaining_time":0.7687608176},
{"learn":[5721.704426],"iteration":230,"passed_time":0.479570336,"remaining_time":0.7660669004},
{"learn":[5717.858772],"iteration":231,"passed_time":0.4815712183,"remaining_time":0.7638715876},
{"learn":[5712.013742],"iteration":232,"passed_time":0.4839319468,"remaining_time":0.7622447402},
{"learn":[5709.74325],"iteration":233,"passed_time":0.4857037224,"remaining_time":0.7596904375},
{"learn":[5706.792507],"iteration":234,"passed_time":0.4878316775,"remaining_time":0.7576960097},
{"learn":[5704.993596],"iteration":235,"passed_time":0.4895569557,"remaining_time":0.7550793724},
{"learn":[5703.257631],"iteration":236,"passed_time":0.4912180731,"remaining_time":0.7523719854},
{"learn":[5699.747974],"iteration":237,"passed_time":0.4960973086,"remaining_time":0.7545681753},
{"learn":[5696.686372],"iteration":238,"passed_time":0.4997051036,"remaining_time":0.7547846962},
{"learn":[5694.178095],"iteration":239,"passed_time":0.5043681903,"remaining_time":0.7565522854},
{"learn":[5692.671175],"iteration":240,"passed_time":0.5070355604,"remaining_time":0.7552936355},
{"learn":[5690.253474],"iteration":241,"passed_time":0.5089504485,"remaining_time":0.7529101676},
{"learn":[5686.980854],"iteration":242,"passed_time":0.5105819432,"remaining_time":0.7501142129},
{"learn":[5683.362814],"iteration":243,"passed_time":0.5121285288,"remaining_time":0.747203919},
{"learn":[5680.123865],"iteration":244,"passed_time":0.5142140703,"remaining_time":0.7450856936},
{"learn":[5677.680279],"iteration":245,"passed_time":0.5162113278,"remaining_time":0.7428406912},
{"learn":[5673.912299],"iteration":246,"passed_time":0.5181163007,"remaining_time":0.7404658063},
{"learn":[5671.555056],"iteration":247,"passed_time":0.5199966916,"remaining_time":0.7380598204},
{"learn":[5667.924374],"iteration":248,"passed_time":0.5220912744,"remaining_time":0.7359599892},
{"learn":[5665.302936],"iteration":249,"passed_time":0.5240043307,"remaining_time":0.7336060629},
{"learn":[5660.992002],"iteration":250,"passed_time":0.5260380433,"remaining_time":0.7314234148},
{"learn":[5658.702391],"iteration":251,"passed_time":0.5278537314,"remaining_time":0.7289408671},
{"learn":[5654.741356],"iteration":252,"passed_time":0.5297665366,"remaining_time":0.7265967914},
{"learn":[5650.458199],"iteration":253,"passed_time":0.531416155,"remaining_time":0.7238975969},
{"learn":[5646.510706],"iteration":254,"passed_time":0.5338628766,"remaining_time":0.7222850684},
{"learn":[5643.718684],"iteration":255,"passed_time":0.5355014538,"remaining_time":0.7195800786},
{"learn":[5641.802947],"iteration":256,"passed_time":0.5373356404,"remaining_time":0.7171444539},
{"learn":[5638.839272],"iteration":257,"passed_time":0.5389485526,"remaining_time":0.7144201744},
{"learn":[5634.502888],"iteration":258,"passed_time":0.540609795,"remaining_time":0.7117681085},
{"learn":[5631.846601],"iteration":259,"passed_time":0.5425581394,"remaining_time":0.7094991054},
{"learn":[5627.952148],"iteration":260,"passed_time":0.5445397312,"remaining_time":0.7072757429},
{"learn":[5625.914394],"iteration":261,"passed_time":0.5462626767,"remaining_time":0.7047205524},
{"learn":[5623.832846],"iteration":262,"passed_time":0.5478432165,"remaining_time":0.7019892166},
{"learn":[5620.46668],"iteration":263,"passed_time":0.5497049849,"remaining_time":0.6996245262},
{"learn":[5616.350261],"iteration":264,"passed_time":0.5523790624,"remaining_time":0.6982905128},
{"learn":[5613.981414],"iteration":265,"passed_time":0.5550082695,"remaining_time":0.6968900828},
{"learn":[5609.720793],"iteration":266,"passed_time":0.5580091969,"remaining_time":0.6959440546},
{"learn":[5607.760032],"iteration":267,"passed_time":0.5598290936,"remaining_time":0.6935196235},
{"learn":[5605.455874],"iteration":268,"passed_time":0.5618998033,"remaining_time":0.6914083082},
{"learn":[5600.088278],"iteration":269,"passed_time":0.563482093,"remaining_time":0.6887003359},
{"learn":[5595.129523],"iteration":270,"passed_time":0.5654542686,"remaining_time":0.6864740013},
{"learn":[5591.242],"iteration":271,"passed_time":0.5673199946,"remaining_time":0.68412117},
{"learn":[5589.433097],"iteration":272,"passed_time":0.5689929031,"remaining_time":0.6815409498},
{"learn":[5587.250382],"iteration":273,"passed_time":0.5707135157,"remaining_time":0.6790241099},
{"learn":[5584.329816],"iteration":274,"passed_time":0.5726672767,"remaining_time":0.6767885998},
{"learn":[5581.610848],"iteration":275,"passed_time":0.5752491956,"remaining_time":0.675292534},
{"learn":[5578.164532],"iteration":276,"passed_time":0.5793207045,"remaining_time":0.6755255869},
{"learn":[5576.659186],"iteration":277,"passed_time":0.5827862609,"remaining_time":0.675025813},
{"learn":[5574.829422],"iteration":278,"passed_time":0.5853255582,"remaining_time":0.673439083},
{"learn":[5570.457916],"iteration":279,"passed_time":0.5872369476,"remaining_time":0.6711279401},
{"learn":[5567.511819],"iteration":280,"passed_time":0.5888043224,"remaining_time":0.6684291062},
{"learn":[5564.89812],"iteration":281,"passed_time":0.5908614502,"remaining_time":0.6662905715},
{"learn":[5560.211774],"iteration":282,"passed_time":0.5926450578,"remaining_time":0.6638462308},
{"learn":[5558.278951],"iteration":283,"passed_time":0.5943375477,"remaining_time":0.6613051587},
{"learn":[5556.401417],"iteration":284,"passed_time":0.5960177056,"remaining_time":0.6587564114},
{"learn":[5553.346423],"iteration":285,"passed_time":0.5979400101,"remaining_time":0.6564795915},
{"learn":[5551.181138],"iteration":286,"passed_time":0.5997749466,"remaining_time":0.6541099592},
{"learn":[5548.237517],"iteration":287,"passed_time":0.6017521218,"remaining_time":0.6518981319},
{"learn":[5545.866034],"iteration":288,"passed_time":0.6036986744,"remaining_time":0.6496549748},
{"learn":[5543.478549],"iteration":289,"passed_time":0.6054481177,"remaining_time":0.6472031603},
{"learn":[5540.461624],"iteration":290,"passed_time":0.6074304184,"remaining_time":0.645003434},
{"learn":[5537.510407],"iteration":291,"passed_time":0.6093103524,"remaining_time":0.642697221},
{"learn":[5533.021565],"iteration":292,"passed_time":0.6112349077,"remaining_time":0.6404406712},
{"learn":[5530.051973],"iteration":293,"passed_time":0.6132264567,"remaining_time":0.638256108},
{"learn":[5526.386544],"iteration":294,"passed_time":0.6151510531,"remaining_time":0.6360036311},
{"learn":[5523.274869],"iteration":295,"passed_time":0.6176682681,"remaining_time":0.6343620051},
{"learn":[5521.455381],"iteration":296,"passed_time":0.6195426595,"remaining_time":0.6320586728},
{"learn":[5518.601458],"iteration":297,"passed_time":0.621352057,"remaining_time":0.6296923531},
{"learn":[5517.019538],"iteration":298,"passed_time":0.6234870526,"remaining_time":0.6276575345},
{"learn":[5515.326048],"iteration":299,"passed_time":0.6252955332,"remaining_time":0.6252955332},
{"learn":[5510.13952],"iteration":300,"passed_time":0.6270580175,"remaining_time":0.622891519},
{"learn":[5508.54639],"iteration":301,"passed_time":0.6288877054,"remaining_time":0.6205580669},
{"learn":[5504.885045],"iteration":302,"passed_time":0.6303877517,"remaining_time":0.6179048259},
{"learn":[5501.337487],"iteration":303,"passed_time":0.6326120331,"remaining_time":0.615964348},
{"learn":[5497.170861],"iteration":304,"passed_time":0.6342593186,"remaining_time":0.6134639311},
{"learn":[5494.32847],"iteration":305,"passed_time":0.6363783994,"remaining_time":0.6114223837},
{"learn":[5490.924244],"iteration":306,"passed_time":0.6384136529,"remaining_time":0.6093003267},
{"learn":[5487.633416],"iteration":307,"passed_time":0.6399651121,"remaining_time":0.6067201712},
{"learn":[5482.997293],"iteration":308,"passed_time":0.641606689,"remaining_time":0.6042315421},
{"learn":[5479.326866],"iteration":309,"passed_time":0.6435185774,"remaining_time":0.6020012498},
{"learn":[5477.834546],"iteration":310,"passed_time":0.6453358483,"remaining_time":0.5996850809},
{"learn":[5475.841857],"iteration":311,"passed_time":0.6472111566,"remaining_time":0.597425683},
{"learn":[5471.885303],"iteration":312,"passed_time":0.6492001648,"remaining_time":0.5952729946},
{"learn":[5468.59342],"iteration":313,"passed_time":0.6510366012,"remaining_time":0.592982382},
{"learn":[5465.736428],"iteration":314,"passed_time":0.6532051361,"remaining_time":0.5909951231},
{"learn":[5463.563525],"iteration":315,"passed_time":0.6566650268,"remaining_time":0.5901673026},
{"learn":[5460.86588],"iteration":316,"passed_time":0.6591828258,"remaining_time":0.5884818287},
{"learn":[5458.079533],"iteration":317,"passed_time":0.6611068802,"remaining_time":0.5862645919},
{"learn":[5456.6196],"iteration":318,"passed_time":0.6627106682,"remaining_time":0.5837670776},
{"learn":[5452.691081],"iteration":319,"passed_time":0.664541522,"remaining_time":0.5814738318},
{"learn":[5451.371578],"iteration":320,"passed_time":0.666345336,"remaining_time":0.579159965},
{"learn":[5447.306838],"iteration":321,"passed_time":0.6678883378,"remaining_time":0.5766240929},
{"learn":[5445.012567],"iteration":322,"passed_time":0.6728275685,"remaining_time":0.5770069241},
{"learn":[5441.363707],"iteration":323,"passed_time":0.6756478434,"remaining_time":0.5755518666},
{"learn":[5437.576229],"iteration":324,"passed_time":0.6776054791,"remaining_time":0.5733584823},
{"learn":[5434.919438],"iteration":325,"passed_time":0.6793270916,"remaining_time":0.570968169},
{"learn":[5429.819599],"iteration":326,"passed_time":0.6815367062,"remaining_time":0.5689893603},
{"learn":[5428.776758],"iteration":327,"passed_time":0.683142828,"remaining_time":0.5665086866},
{"learn":[5426.036985],"iteration":328,"passed_time":0.6856208382,"remaining_time":0.5647515111},
{"learn":[5422.523894],"iteration":329,"passed_time":0.6875282689,"remaining_time":0.5625231291},
{"learn":[5420.194239],"iteration":330,"passed_time":0.6890867695,"remaining_time":0.5600131148},
{"learn":[5417.518784],"iteration":331,"passed_time":0.6909702441,"remaining_time":0.5577711609},
{"learn":[5415.818602],"iteration":332,"passed_time":0.6933199725,"remaining_time":0.5559052032},
{"learn":[5414.005429],"iteration":333,"passed_time":0.6968194012,"remaining_time":0.5549519782},
{"learn":[5410.71678],"iteration":334,"passed_time":0.7007125064,"remaining_time":0.5542949677},
{"learn":[5408.427363],"iteration":335,"passed_time":0.7062149841,"remaining_time":0.5548832018},
{"learn":[5405.463136],"iteration":336,"passed_time":0.7078884335,"remaining_time":0.5524470564},
{"learn":[5404.663279],"iteration":337,"passed_time":0.7112659138,"remaining_time":0.5513363001},
{"learn":[5403.167345],"iteration":338,"passed_time":0.7177759771,"remaining_time":0.5526239824},
{"learn":[5401.400967],"iteration":339,"passed_time":0.7196109976,"remaining_time":0.5502907629},
{"learn":[5399.840253],"iteration":340,"passed_time":0.7215299284,"remaining_time":0.5480241978},
{"learn":[5397.332075],"iteration":341,"passed_time":0.7232478743,"remaining_time":0.5456080455},
{"learn":[5395.625477],"iteration":342,"passed_time":0.7247774182,"remaining_time":0.5430548002},
{"learn":[5392.160423],"iteration":343,"passed_time":0.7266744337,"remaining_time":0.5407809739},
{"learn":[5389.268861],"iteration":344,"passed_time":0.7283506339,"remaining_time":0.5383461207},
{"learn":[5386.894873],"iteration":345,"passed_time":0.7299688387,"remaining_time":0.5358730781},
{"learn":[5383.988666],"iteration":346,"passed_time":0.7316677031,"remaining_time":0.533463772},
{"learn":[5381.15057],"iteration":347,"passed_time":0.7335753428,"remaining_time":0.531209731},
{"learn":[5380.044897],"iteration":348,"passed_time":0.7354835234,"remaining_time":0.5289580641},
{"learn":[5376.789841],"iteration":349,"passed_time":0.7373567899,"remaining_time":0.5266834214},
{"learn":[5374.05426],"iteration":350,"passed_time":0.7389692452,"remaining_time":0.5242260457},
{"learn":[5372.256272],"iteration":351,"passed_time":0.7407883919,"remaining_time":0.5219190943},
{"learn":[5371.187889],"iteration":352,"passed_time":0.7425103795,"remaining_time":0.5195469227},
{"learn":[5367.594424],"iteration":353,"passed_time":0.744157123,"remaining_time":0.5171261363},
{"learn":[5365.077156],"iteration":354,"passed_time":0.7462222501,"remaining_time":0.5149984543},
{"learn":[5363.653529],"iteration":355,"passed_time":0.7480668109,"remaining_time":0.512719949},
{"learn":[5359.271841],"iteration":356,"passed_time":0.749868375,"remaining_time":0.5104146082},
{"learn":[5357.831946],"iteration":357,"passed_time":0.7519622499,"remaining_time":0.5083096773},
{"learn":[5354.451422],"iteration":358,"passed_time":0.7537124442,"remaining_time":0.505974092},
{"learn":[5352.39508],"iteration":359,"passed_time":0.7555505054,"remaining_time":0.5037003369},
{"learn":[5349.998245],"iteration":360,"passed_time":0.7572159975,"remaining_time":0.5013147462},
{"learn":[5347.731064],"iteration":361,"passed_time":0.7590707654,"remaining_time":0.499057575},
{"learn":[5346.661832],"iteration":362,"passed_time":0.760942283,"remaining_time":0.4968135567},
{"learn":[5345.078457],"iteration":363,"passed_time":0.762846298,"remaining_time":0.4945926547},
{"learn":[5342.191922],"iteration":364,"passed_time":0.7645434545,"remaining_time":0.4922403063},
{"learn":[5340.294403],"iteration":365,"passed_time":0.7672526132,"remaining_time":0.490538556},
{"learn":[5337.613998],"iteration":366,"passed_time":0.7691376717,"remaining_time":0.4883081131},
{"learn":[5336.187283],"iteration":367,"passed_time":0.7712113812,"remaining_time":0.4861984794},
{"learn":[5333.102025],"iteration":368,"passed_time":0.7728530411,"remaining_time":0.4838185704},
{"learn":[5330.839551],"iteration":369,"passed_time":0.7746159833,"remaining_time":0.4815180437},
{"learn":[5328.592318],"iteration":370,"passed_time":0.7764820844,"remaining_time":0.4792840898},
{"learn":[5326.143659],"iteration":371,"passed_time":0.778428179,"remaining_time":0.477101142},
{"learn":[5324.608255],"iteration":372,"passed_time":0.7802423682,"remaining_time":0.4748391892},
{"learn":[5323.348434],"iteration":373,"passed_time":0.7828382859,"remaining_time":0.4730520124},
{"learn":[5320.538153],"iteration":374,"passed_time":0.7846830557,"remaining_time":0.4708098334},
{"learn":[5316.295451],"iteration":375,"passed_time":0.7863183831,"remaining_time":0.4684449942},
{"learn":[5314.866875],"iteration":376,"passed_time":0.7882165236,"remaining_time":0.4662394821},
{"learn":[5313.277467],"iteration":377,"passed_time":0.7900438777,"remaining_time":0.4639940234},
{"learn":[5310.507935],"iteration":378,"passed_time":0.791893896,"remaining_time":0.4617639868},
{"learn":[5309.321311],"iteration":379,"passed_time":0.7938044515,"remaining_time":0.4595709982},
{"learn":[5306.989967],"iteration":380,"passed_time":0.7953145809,"remaining_time":0.457149326},
{"learn":[5303.989344],"iteration":381,"passed_time":0.7971069798,"remaining_time":0.454893512},
{"learn":[5302.174292],"iteration":382,"passed_time":0.7992568502,"remaining_time":0.452842654},
{"learn":[5300.110662],"iteration":383,"passed_time":0.8011603652,"remaining_time":0.4506527054},
{"learn":[5297.575758],"iteration":384,"passed_time":0.8030214666,"remaining_time":0.4484405593},
{"learn":[5294.764651],"iteration":385,"passed_time":0.8048659854,"remaining_time":0.4462210385},
{"learn":[5292.622641],"iteration":386,"passed_time":0.8066322194,"remaining_time":0.4439603688},
{"learn":[5290.031804],"iteration":387,"passed_time":0.8083892871,"remaining_time":0.4416972393},
{"learn":[5287.854364],"iteration":388,"passed_time":0.8099300811,"remaining_time":0.4393194013},
{"learn":[5285.840085],"iteration":389,"passed_time":0.8117814333,"remaining_time":0.4371130795},
{"learn":[5282.061139],"iteration":390,"passed_time":0.8139913819,"remaining_time":0.4351002527},
{"learn":[5280.751043],"iteration":391,"passed_time":0.8155247174,"remaining_time":0.4327274011},
{"learn":[5279.42036],"iteration":392,"passed_time":0.8173152415,"remaining_time":0.4304942875},
{"learn":[5276.84227],"iteration":393,"passed_time":0.8190974322,"remaining_time":0.4282590635},
{"learn":[5274.527037],"iteration":394,"passed_time":0.8209834487,"remaining_time":0.4260800177},
{"learn":[5272.579185],"iteration":395,"passed_time":0.8225640305,"remaining_time":0.4237451066},
{"learn":[5272.045937],"iteration":396,"passed_time":0.8244687124,"remaining_time":0.4215797194},
{"learn":[5269.905805],"iteration":397,"passed_time":0.8263876422,"remaining_time":0.4194228737},
{"learn":[5266.112105],"iteration":398,"passed_time":0.8282880745,"remaining_time":0.4172579022},
{"learn":[5264.981738],"iteration":399,"passed_time":0.8300366009,"remaining_time":0.4150183005},
{"learn":[5262.391809],"iteration":400,"passed_time":0.8316197245,"remaining_time":0.4126990653},
{"learn":[5261.041481],"iteration":401,"passed_time":0.8331841836,"remaining_time":0.4103742994},
{"learn":[5259.85939],"iteration":402,"passed_time":0.8350748667,"remaining_time":0.408212776},
{"learn":[5257.772531],"iteration":403,"passed_time":0.8366971962,"remaining_time":0.4059224021},
{"learn":[5256.938729],"iteration":404,"passed_time":0.8382578626,"remaining_time":0.4036056375},
{"learn":[5255.867005],"iteration":405,"passed_time":0.8407937021,"remaining_time":0.401758567},
{"learn":[5254.736722],"iteration":406,"passed_time":0.8425184394,"remaining_time":0.399523486},
{"learn":[5252.626786],"iteration":407,"passed_time":0.844741512,"remaining_time":0.3975254174},
{"learn":[5250.415891],"iteration":408,"passed_time":0.8464062131,"remaining_time":0.3952654931},
{"learn":[5248.916613],"iteration":409,"passed_time":0.8485180445,"remaining_time":0.3932156791},
{"learn":[5247.668138],"iteration":410,"passed_time":0.8501362073,"remaining_time":0.3909385479},
{"learn":[5245.740045],"iteration":411,"passed_time":0.851680293,"remaining_time":0.3886308133},
{"learn":[5244.565862],"iteration":412,"passed_time":0.8533372857,"remaining_time":0.3863778993},
{"learn":[5242.446115],"iteration":413,"passed_time":0.8548802875,"remaining_time":0.3840766509},
{"learn":[5240.952863],"iteration":414,"passed_time":0.8567563878,"remaining_time":0.3819275463},
{"learn":[5239.100414],"iteration":415,"passed_time":0.858694816,"remaining_time":0.3798073225},
{"learn":[5237.818588],"iteration":416,"passed_time":0.8610314215,"remaining_time":0.3778627101},
{"learn":[5236.719201],"iteration":417,"passed_time":0.8629297279,"remaining_time":0.3757253839},
{"learn":[5234.952972],"iteration":418,"passed_time":0.8647693311,"remaining_time":0.3735638399},
{"learn":[5233.632173],"iteration":419,"passed_time":0.866360912,"remaining_time":0.3712975337},
{"learn":[5231.713281],"iteration":420,"passed_time":0.8682553438,"remaining_time":0.3691631984},
{"learn":[5229.375846],"iteration":421,"passed_time":0.8700873645,"remaining_time":0.3670036751},
{"learn":[5226.828187],"iteration":422,"passed_time":0.8716735709,"remaining_time":0.3647428417},
{"learn":[5225.247032],"iteration":423,"passed_time":0.8739825115,"remaining_time":0.3627851935},
{"learn":[5223.017488],"iteration":424,"passed_time":0.8758070329,"remaining_time":0.3606264253},
{"learn":[5222.522959],"iteration":425,"passed_time":0.8776513016,"remaining_time":0.3584772922},
{"learn":[5218.168708],"iteration":426,"passed_time":0.8802514281,"remaining_time":0.3566358245},
{"learn":[5215.122982],"iteration":427,"passed_time":0.8824301291,"remaining_time":0.3546214538},
{"learn":[5213.934553],"iteration":428,"passed_time":0.8843739329,"remaining_time":0.3525126866},
{"learn":[5211.772814],"iteration":429,"passed_time":0.8859906369,"remaining_time":0.3502753681},
{"learn":[5209.927243],"iteration":430,"passed_time":0.8878949848,"remaining_time":0.348153718},
{"learn":[5206.553466],"iteration":431,"passed_time":0.8898064992,"remaining_time":0.3460358608},
{"learn":[5202.972025],"iteration":432,"passed_time":0.89142537,"remaining_time":0.3438060896},
{"learn":[5201.010517],"iteration":433,"passed_time":0.8932080607,"remaining_time":0.3416417928},
{"learn":[5199.893417],"iteration":434,"passed_time":0.89509591,"remaining_time":0.3395191383},
{"learn":[5196.260837],"iteration":435,"passed_time":0.8971724942,"remaining_time":0.3374685529},
{"learn":[5194.368317],"iteration":436,"passed_time":0.8987313697,"remaining_time":0.3352247443},
{"learn":[5191.265654],"iteration":437,"passed_time":0.9004353587,"remaining_time":0.3330377354},
{"learn":[5187.529225],"iteration":438,"passed_time":0.9023172085,"remaining_time":0.3309181562},
{"learn":[5186.541553],"iteration":439,"passed_time":0.9040824005,"remaining_time":0.3287572366},
{"learn":[5184.446294],"iteration":440,"passed_time":0.9058945059,"remaining_time":0.3266150259},
{"learn":[5182.203103],"iteration":441,"passed_time":0.9074435492,"remaining_time":0.3243802732},
{"learn":[5179.739857],"iteration":442,"passed_time":0.9093359401,"remaining_time":0.3222702993},
{"learn":[5177.333975],"iteration":443,"passed_time":0.9111508792,"remaining_time":0.3201340927},
{"learn":[5175.003271],"iteration":444,"passed_time":0.9130435611,"remaining_time":0.3180264089},
{"learn":[5172.245374],"iteration":445,"passed_time":0.9146597651,"remaining_time":0.3158242238},
{"learn":[5170.552973],"iteration":446,"passed_time":0.9162416388,"remaining_time":0.3136129099},
{"learn":[5168.468436],"iteration":447,"passed_time":0.9178721336,"remaining_time":0.3114209025},
{"learn":[5167.942908],"iteration":448,"passed_time":0.9195153775,"remaining_time":0.3092356837},
{"learn":[5165.992133],"iteration":449,"passed_time":0.9213652718,"remaining_time":0.3071217573},
{"learn":[5164.118439],"iteration":450,"passed_time":0.9232012082,"remaining_time":0.3050043903},
{"learn":[5160.49753],"iteration":451,"passed_time":0.9249627336,"remaining_time":0.3028639039},
{"learn":[5158.098391],"iteration":452,"passed_time":0.926849208,"remaining_time":0.300765637},
{"learn":[5156.926768],"iteration":453,"passed_time":0.9289109594,"remaining_time":0.2987246698},
{"learn":[5154.004935],"iteration":454,"passed_time":0.9307028163,"remaining_time":0.2965976008},
{"learn":[5152.073275],"iteration":455,"passed_time":0.9326906576,"remaining_time":0.2945338919},
{"learn":[5150.956205],"iteration":456,"passed_time":0.9343705645,"remaining_time":0.2923741591},
{"learn":[5148.018585],"iteration":457,"passed_time":0.9361819199,"remaining_time":0.2902572765},
{"learn":[5145.861654],"iteration":458,"passed_time":0.9380137737,"remaining_time":0.288148022},
{"learn":[5144.224045],"iteration":459,"passed_time":0.9398538348,"remaining_time":0.2860424714},
{"learn":[5144.082594],"iteration":460,"passed_time":0.9416873554,"remaining_time":0.2839361006},
{"learn":[5142.199292],"iteration":461,"passed_time":0.9435376237,"remaining_time":0.2818359136},
{"learn":[5140.211302],"iteration":462,"passed_time":0.9453644778,"remaining_time":0.2797298779},
{"learn":[5140.038969],"iteration":463,"passed_time":0.9472196207,"remaining_time":0.2776333371},
{"learn":[5138.081401],"iteration":464,"passed_time":0.9486555891,"remaining_time":0.2754161388},
{"learn":[5135.336092],"iteration":465,"passed_time":0.9501130557,"remaining_time":0.2732084753},
{"learn":[5132.65517],"iteration":466,"passed_time":0.9520972723,"remaining_time":0.2711540412},
{"learn":[5130.854674],"iteration":467,"passed_time":0.9539150852,"remaining_time":0.2690529727},
{"learn":[5130.258107],"iteration":468,"passed_time":0.955758313,"remaining_time":0.2669602111},
{"learn":[5128.015595],"iteration":469,"passed_time":0.9581855773,"remaining_time":0.2650300533},
{"learn":[5126.333625],"iteration":470,"passed_time":0.959955561,"remaining_time":0.2629177651},
{"learn":[5124.544095],"iteration":471,"passed_time":0.9618375357,"remaining_time":0.2608372978},
{"learn":[5121.392417],"iteration":472,"passed_time":0.9632689624,"remaining_time":0.2586366982},
{"learn":[5119.569745],"iteration":473,"passed_time":0.964765009,"remaining_time":0.2564565214},
{"learn":[5117.733845],"iteration":474,"passed_time":0.9663526733,"remaining_time":0.2543033351},
{"learn":[5116.097527],"iteration":475,"passed_time":0.9683835111,"remaining_time":0.2522679735},
{"learn":[5114.355215],"iteration":476,"passed_time":0.970214282,"remaining_time":0.2501810413},
{"learn":[5112.466635],"iteration":477,"passed_time":0.9718229445,"remaining_time":0.2480384921},
{"learn":[5110.769844],"iteration":478,"passed_time":0.9733609058,"remaining_time":0.2458803123},
{"learn":[5109.24784],"iteration":479,"passed_time":0.9752136328,"remaining_time":0.2438034082},
{"learn":[5108.275302],"iteration":480,"passed_time":0.9768603764,"remaining_time":0.2416764757},
{"learn":[5106.352968],"iteration":481,"passed_time":0.9787739316,"remaining_time":0.2396168546},
{"learn":[5105.047387],"iteration":482,"passed_time":0.9810574163,"remaining_time":0.2376474487},
{"learn":[5103.824152],"iteration":483,"passed_time":0.9829013941,"remaining_time":0.2355714085},
{"learn":[5102.113139],"iteration":484,"passed_time":0.984655754,"remaining_time":0.2334750757},
{"learn":[5100.184153],"iteration":485,"passed_time":0.9864262377,"remaining_time":0.2313839323},
{"learn":[5098.347099],"iteration":486,"passed_time":0.9882370931,"remaining_time":0.2293034734},
{"learn":[5096.49472],"iteration":487,"passed_time":0.9899652052,"remaining_time":0.2272051291},
{"learn":[5093.82434],"iteration":488,"passed_time":0.992134574,"remaining_time":0.2252084616},
{"learn":[5092.00452],"iteration":489,"passed_time":0.9939935506,"remaining_time":0.2231414093},
{"learn":[5090.178573],"iteration":490,"passed_time":0.9958724416,"remaining_time":0.2210796255},
{"learn":[5088.279826],"iteration":491,"passed_time":0.9977255016,"remaining_time":0.219012915},
{"learn":[5084.389404],"iteration":492,"passed_time":0.9995404407,"remaining_time":0.2169387975},
{"learn":[5082.770222],"iteration":493,"passed_time":1.001402709,"remaining_time":0.2148758849},
{"learn":[5081.099903],"iteration":494,"passed_time":1.003283892,"remaining_time":0.2128177952},
{"learn":[5079.246375],"iteration":495,"passed_time":1.008257036,"remaining_time":0.2114087333},
{"learn":[5076.802847],"iteration":496,"passed_time":1.013779387,"remaining_time":0.2100991486},
{"learn":[5076.459616],"iteration":497,"passed_time":1.016894596,"remaining_time":0.2082796161},
{"learn":[5073.468179],"iteration":498,"passed_time":1.019833112,"remaining_time":0.2064191268},
{"learn":[5071.101962],"iteration":499,"passed_time":1.023399868,"remaining_time":0.2046799736},
{"learn":[5069.426862],"iteration":500,"passed_time":1.027524914,"remaining_time":0.2030438452},
{"learn":[5067.404415],"iteration":501,"passed_time":1.030891687,"remaining_time":0.2012497715},
{"learn":[5066.993696],"iteration":502,"passed_time":1.03405006,"remaining_time":0.199409256},
{"learn":[5065.284306],"iteration":503,"passed_time":1.036587774,"remaining_time":0.1974452903},
{"learn":[5063.981869],"iteration":504,"passed_time":1.040195944,"remaining_time":0.1956804251},
{"learn":[5063.045237],"iteration":505,"passed_time":1.044815116,"remaining_time":0.1940960888},
{"learn":[5060.120388],"iteration":506,"passed_time":1.048514904,"remaining_time":0.1923311362},
{"learn":[5059.122609],"iteration":507,"passed_time":1.05151004,"remaining_time":0.1904309521},
{"learn":[5058.108457],"iteration":508,"passed_time":1.056117631,"remaining_time":0.1888147435},
{"learn":[5055.621865],"iteration":509,"passed_time":1.060426246,"remaining_time":0.1871340434},
{"learn":[5054.32582],"iteration":510,"passed_time":1.062111069,"remaining_time":0.1849860767},
{"learn":[5052.679736],"iteration":511,"passed_time":1.06362874,"remaining_time":0.1828111897},
{"learn":[5051.546094],"iteration":512,"passed_time":1.065544129,"remaining_time":0.1807063143},
{"learn":[5048.658876],"iteration":513,"passed_time":1.067451811,"remaining_time":0.1786008867},
{"learn":[5046.061268],"iteration":514,"passed_time":1.069222795,"remaining_time":0.1764736651},
{"learn":[5045.455743],"iteration":515,"passed_time":1.071451784,"remaining_time":0.1744223834},
{"learn":[5043.460637],"iteration":516,"passed_time":1.073030575,"remaining_time":0.1722660304},
{"learn":[5041.353193],"iteration":517,"passed_time":1.074933798,"remaining_time":0.1701632653},
{"learn":[5039.508441],"iteration":518,"passed_time":1.077018631,"remaining_time":0.168089613},
{"learn":[5038.550757],"iteration":519,"passed_time":1.079380318,"remaining_time":0.1660585104},
{"learn":[5037.554707],"iteration":520,"passed_time":1.080991689,"remaining_time":0.1639123675},
{"learn":[5035.788172],"iteration":521,"passed_time":1.083019111,"remaining_time":0.1618304419},
{"learn":[5034.485532],"iteration":522,"passed_time":1.084578403,"remaining_time":0.1596798031},
{"learn":[5032.863271],"iteration":523,"passed_time":1.086008914,"remaining_time":0.1575127432},
{"learn":[5030.97622],"iteration":524,"passed_time":1.087917053,"remaining_time":0.1554167219},
{"learn":[5030.633282],"iteration":525,"passed_time":1.089702994,"remaining_time":0.1533042234},
{"learn":[5029.664735],"iteration":526,"passed_time":1.091856322,"remaining_time":0.1512438548},
{"learn":[5027.81218],"iteration":527,"passed_time":1.093513772,"remaining_time":0.1491155144},
{"learn":[5025.115146],"iteration":528,"passed_time":1.095322961,"remaining_time":0.1470093199},
{"learn":[5022.180204],"iteration":529,"passed_time":1.097232684,"remaining_time":0.1449175242},
{"learn":[5021.094389],"iteration":530,"passed_time":1.09888526,"remaining_time":0.1427929998},
{"learn":[5019.235477],"iteration":531,"passed_time":1.10042572,"remaining_time":0.1406559191},
{"learn":[5017.873106],"iteration":532,"passed_time":1.102286613,"remaining_time":0.1385613566},
{"learn":[5016.301594],"iteration":533,"passed_time":1.10429037,"remaining_time":0.1364853266},
{"learn":[5014.259966],"iteration":534,"passed_time":1.1060039,"remaining_time":0.1343743056},
{"learn":[5012.923633],"iteration":535,"passed_time":1.107670434,"remaining_time":0.1322591563},
{"learn":[5010.420818],"iteration":536,"passed_time":1.109419503,"remaining_time":0.1301553606},
{"learn":[5009.281485],"iteration":537,"passed_time":1.111273397,"remaining_time":0.1280649639},
{"learn":[5007.926009],"iteration":538,"passed_time":1.113012549,"remaining_time":0.1259624591},
{"learn":[5004.952635],"iteration":539,"passed_time":1.114566217,"remaining_time":0.1238406908},
{"learn":[5003.868125],"iteration":540,"passed_time":1.116255332,"remaining_time":0.1217357941},
{"learn":[5002.393705],"iteration":541,"passed_time":1.118103434,"remaining_time":0.119649445},
{"learn":[5001.51139],"iteration":542,"passed_time":1.119607522,"remaining_time":0.1175278615},
{"learn":[4999.832626],"iteration":543,"passed_time":1.12154566,"remaining_time":0.1154532297},
{"learn":[4998.190143],"iteration":544,"passed_time":1.123344974,"remaining_time":0.1133650891},
{"learn":[4995.88019],"iteration":545,"passed_time":1.124888559,"remaining_time":0.1112527146},
{"learn":[4995.331119],"iteration":546,"passed_time":1.126745202,"remaining_time":0.1091727527},
{"learn":[4993.964513],"iteration":547,"passed_time":1.128672965,"remaining_time":0.1071003543},
{"learn":[4993.299763],"iteration":548,"passed_time":1.130503818,"remaining_time":0.1050194804},
{"learn":[4991.73059],"iteration":549,"passed_time":1.132083484,"remaining_time":0.1029166804},
{"learn":[4989.827455],"iteration":550,"passed_time":1.133939711,"remaining_time":0.1008403736},
{"learn":[4988.218666],"iteration":551,"passed_time":1.135608661,"remaining_time":0.09874857921},
{"learn":[4986.732583],"iteration":552,"passed_time":1.137355938,"remaining_time":0.09666497126},
{"learn":[4985.332112],"iteration":553,"passed_time":1.139010306,"remaining_time":0.09457486298},
{"learn":[4984.439221],"iteration":554,"passed_time":1.140775206,"remaining_time":0.09249528701},
{"learn":[4983.157963],"iteration":555,"passed_time":1.142313709,"remaining_time":0.09039892658},
{"learn":[4982.38906],"iteration":556,"passed_time":1.144136688,"remaining_time":0.08832653068},
{"learn":[4980.83975],"iteration":557,"passed_time":1.145628111,"remaining_time":0.08623007287},
{"learn":[4979.070022],"iteration":558,"passed_time":1.147168654,"remaining_time":0.08413938249},
{"learn":[4977.470878],"iteration":559,"passed_time":1.148986425,"remaining_time":0.08207045892},
{"learn":[4975.443248],"iteration":560,"passed_time":1.150480597,"remaining_time":0.07997993452},
{"learn":[4973.996452],"iteration":561,"passed_time":1.152691628,"remaining_time":0.07794000332},
{"learn":[4972.702478],"iteration":562,"passed_time":1.154315373,"remaining_time":0.07586086824},
{"learn":[4971.57472],"iteration":563,"passed_time":1.156026612,"remaining_time":0.07378893267},
{"learn":[4970.634006],"iteration":564,"passed_time":1.157608486,"remaining_time":0.07171026017},
{"learn":[4969.194772],"iteration":565,"passed_time":1.159423008,"remaining_time":0.06964731848},
{"learn":[4967.358187],"iteration":566,"passed_time":1.161394183,"remaining_time":0.06759437046},
{"learn":[4965.903862],"iteration":567,"passed_time":1.163224454,"remaining_time":0.06553377207},
{"learn":[4965.376544],"iteration":568,"passed_time":1.165664926,"remaining_time":0.06350722797},
{"learn":[4963.819846],"iteration":569,"passed_time":1.16721097,"remaining_time":0.06143215631},
{"learn":[4962.234043],"iteration":570,"passed_time":1.169069906,"remaining_time":0.05937482883},
{"learn":[4959.590201],"iteration":571,"passed_time":1.171056664,"remaining_time":0.05732445208},
{"learn":[4957.799369],"iteration":572,"passed_time":1.172944346,"remaining_time":0.05526962888},
{"learn":[4956.048345],"iteration":573,"passed_time":1.174824987,"remaining_time":0.0532150691},
{"learn":[4954.57482],"iteration":574,"passed_time":1.177586559,"remaining_time":0.05119941559},
{"learn":[4953.29309],"iteration":575,"passed_time":1.180256095,"remaining_time":0.04917733731},
{"learn":[4951.168631],"iteration":576,"passed_time":1.181820179,"remaining_time":0.04710894993},
{"learn":[4948.810005],"iteration":577,"passed_time":1.183819227,"remaining_time":0.04505886331},
{"learn":[4947.720347],"iteration":578,"passed_time":1.185584461,"remaining_time":0.04300047268},
{"learn":[4945.530159],"iteration":579,"passed_time":1.187335696,"remaining_time":0.04094261022},
{"learn":[4943.967512],"iteration":580,"passed_time":1.189025436,"remaining_time":0.03888379224},
{"learn":[4942.83989],"iteration":581,"passed_time":1.190949033,"remaining_time":0.03683347524},
{"learn":[4941.379146],"iteration":582,"passed_time":1.192489952,"remaining_time":0.03477243427},
{"learn":[4939.7295],"iteration":583,"passed_time":1.194270352,"remaining_time":0.03271973566},
{"learn":[4937.161936],"iteration":584,"passed_time":1.196137911,"remaining_time":0.03067020284},
{"learn":[4935.471153],"iteration":585,"passed_time":1.198017386,"remaining_time":0.02862157576},
{"learn":[4933.752463],"iteration":586,"passed_time":1.199771038,"remaining_time":0.02657073848},
{"learn":[4930.580949],"iteration":587,"passed_time":1.201359786,"remaining_time":0.02451754665},
{"learn":[4927.386544],"iteration":588,"passed_time":1.203174807,"remaining_time":0.02247015768},
{"learn":[4925.456708],"iteration":589,"passed_time":1.205118485,"remaining_time":0.02042573703},
{"learn":[4923.921056],"iteration":590,"passed_time":1.207003084,"remaining_time":0.01838075763},
{"learn":[4922.724604],"iteration":591,"passed_time":1.208862394,"remaining_time":0.01633597829},
{"learn":[4921.100457],"iteration":592,"passed_time":1.210382314,"remaining_time":0.01428781821},
{"learn":[4919.124758],"iteration":593,"passed_time":1.212222875,"remaining_time":0.01224467551},
{"learn":[4917.986308],"iteration":594,"passed_time":1.2141116,"remaining_time":0.01020261848},
{"learn":[4916.33937],"iteration":595,"passed_time":1.217791598,"remaining_time":0.008173097972},
{"learn":[4915.225525],"iteration":596,"passed_time":1.219636284,"remaining_time":0.006128825546},
{"learn":[4913.471439],"iteration":597,"passed_time":1.221315733,"remaining_time":0.004084668002},
{"learn":[4912.54293],"iteration":598,"passed_time":1.223204832,"remaining_time":0.002042078183},
{"learn":[4911.799034],"iteration":599,"passed_time":1.22479608,"remaining_time":0}
]}